dbt_jobs_as_code-1.13.1.dist-info/METADATA
dbt_jobs_as_code-1.13.1.dist-info/WHEEL
dbt_jobs_as_code-1.13.1.dist-info/entry_points.txt
dbt_jobs_as_code-1.13.1.dist-info/licenses/LICENSE
dbt_jobs_as_code/__init__.py
dbt_jobs_as_code/client/__init__.py
dbt_jobs_as_code/cloud_yaml_mapping/change_set.py
dbt_jobs_as_code/cloud_yaml_mapping/validate_link.py
dbt_jobs_as_code/exporter/__init__.py
dbt_jobs_as_code/exporter/export.py
dbt_jobs_as_code/importer/__init__.py
dbt_jobs_as_code/loader/__init__.py
dbt_jobs_as_code/loader/load.py
dbt_jobs_as_code/main.py
dbt_jobs_as_code/schemas/__init__.py
dbt_jobs_as_code/schemas/common_types.py
dbt_jobs_as_code/schemas/config.py
dbt_jobs_as_code/schemas/custom_environment_variable.py
dbt_jobs_as_code/schemas/job.py
dbt_jobs_as_code/schemas/load_job_schema.json
dbt_jobs_as_code-1.13.1.dist-info/RECORD
