Metadata-Version: 2.1
Name: dbt-jobs-as-code
Version: 1.13.1
Summary: A CLI to allow defining dbt Cloud jobs as code
Keywords: dbt,dbt Cloud
Author-Email: dbt Labs <info@dbtlabs.com>
License: Apache License 2.0
Project-URL: repository, https://github.com/dbt-labs/dbt-jobs-as-code.git
Requires-Python: >=3.9
Requires-Dist: click<9.0.0,>=8.1.3
Requires-Dist: requests<3.0.0,>=2.32.0
Requires-Dist: loguru<1.0.0,>=0.6.0
Requires-Dist: deepdiff<9.0.0,>=8.6.1
Requires-Dist: pydantic<3.0.0,>=2.12.0
Requires-Dist: croniter<2.0.0,>=1.3.8
Requires-Dist: ruamel-yaml<1.0.0,>=0.17.21
Requires-Dist: rich<13.0.0,>=12.6.0
Requires-Dist: PyYAML<7.0.0,>=6.0.1
Requires-Dist: python-dateutil<3.0,>=2.9
Requires-Dist: beartype<1.0.0,>=0.18.5
Requires-Dist: jinja2<4.0.0,>=3.1.5
Requires-Dist: importlib-metadata<7,>=6.0
